{
  "fields": [
    {
      "name": "id",
      "type": "uuid"
    },
    {
      "name": "created_on",
      "type": "timestamp without time zone"
    },
    {
      "name": "created_by_id",
      "type": "uuid"
    },
    {
      "name": "modified_on",
      "type": "timestamp without time zone"
    },
    {
      "name": "modified_by_id",
      "type": "uuid"
    },
    {
      "name": "contact_id",
      "type": "uuid"
    },
    {
      "name": "cover_id",
      "type": "uuid",
      "isFk": true,
      "ref": "cover"
    },
    {
      "name": "setup_date",
      "type": "timestamp without time zone"
    }
  ],
  "detailsTabs": [],
  "custom": {
    "listFields": [],
    "showFields": [],
    "createFields": [],
    "editFields": [],
    "showDetailsTabs": []
  },
  "metaUpdatedAt": "2025-06-19T12:06:13.027Z"
}