{
  "fields": [
    {
      "name": "id",
      "type": "uuid"
    },
    {
      "name": "created_on",
      "type": "timestamp without time zone"
    },
    {
      "name": "created_by_id",
      "type": "uuid"
    },
    {
      "name": "modified_on",
      "type": "timestamp without time zone"
    },
    {
      "name": "modified_by_id",
      "type": "uuid"
    },
    {
      "name": "service_item_id",
      "type": "uuid",
      "isFk": true,
      "ref": "service_item"
    },
    {
      "name": "service_pact_id",
      "type": "uuid",
      "isFk": true,
      "ref": "service_pact"
    },
    {
      "name": "reaction_time_value",
      "type": "integer"
    },
    {
      "name": "reaction_time_unit_id",
      "type": "uuid",
      "isFk": true,
      "ref": "time_unit"
    },
    {
      "name": "solution_time_value",
      "type": "integer"
    },
    {
      "name": "solution_time_unit_id",
      "type": "uuid",
      "isFk": true,
      "ref": "time_unit"
    },
    {
      "name": "calendar_id",
      "type": "uuid",
      "isFk": true,
      "ref": "calendar"
    },
    {
      "name": "reaction_time",
      "type": "character varying"
    },
    {
      "name": "solution_time",
      "type": "character varying"
    },
    {
      "name": "concat_name",
      "type": "character varying"
    }
  ],
  "detailsTabs": [],
  "custom": {
    "listFields": [],
    "showFields": [],
    "createFields": [],
    "editFields": [],
    "showDetailsTabs": []
  },
  "metaUpdatedAt": "2025-06-19T09:28:41.886Z"
}